DDCOProject/lib.v
module and2 (input wire i0, i1, output wire o);
  assign o = i0 & i1;
endmodule

module or2 (input wire i0, i1, output wire o);
  assign o = i0 | i1;
endmodule

module and3 (input wire i0, i1, i2, output wire o);
   wire t;
   and2 and2_0 (i0, i1, t);
   and2 and2_1 (i2, t, o);
endmodule

module or3 (input wire i0, i1, i2, output wire o);
   wire t;
   or2 or2_0 (i0, i1, t);
   or2 or2_1 (i2, t, o);
endmodule

DDCOProject/seven_segment.v
module a_segment(input wire a, b, c, d, output wire out); //a_segment = a + c + bd + b'd'
    wire t0, t1, t2;
    and2 a0(b, d, t1);
    and2 a1(!b, !d, t2);
    or2 o0(a, c, t0);
    or3 o1(t0, t1, t2, out);
endmodule

module b_segment(input wire a, b, c, d, output wire out); //b_segment = b' + c'd' + cd
    wire t0, t1;
    and2 a0(!c, !d, t0);
    and2 a1(c, d, t1);
    or3 o1(!b, t0, t1, out);
endmodule

module c_segment(input wire a, b, c, d, output wire out); //c_segment = b + c' + d
    or3 o0(b, !c, d, out);
endmodule

module d_segment(input wire a, b, c, d, output wire out); //d_segment = b'd' + cd' + bc'd + b'c + a
    wire t0, t1, t2, t3, t4;
    and2 a0(!b, !d, t0);
    and2 a1(c, !d, t1);
    and3 a2(b, !c, d, t2);
    and2 a3(!b, c, t3);
    or3 o0(t0, t1, t2, t4);
    or3 o1(t4, t3, a, out);
endmodule

module e_segment(input wire a, b, c, d, output wire out); //e_segment = b'd' + cd'
    wire t0, t1;
    and2 a0(!b, !d, t0);
    and2 a1(c, !d, t1);
    or2 o0(t0, t1, out);
endmodule

module f_segment(input wire a, b, c, d, output wire out); //f_segment = a + c'd' + bc' + bd'
    wire t0, t1, t2, t3;
    and2 a0(!c, !d, t0);
    and2 a1(b, !c, t1);
    and2 a2(b, !d, t2);
    or3 o0(t0, t1, t2, t3);
    or2 o1(a, t3, out);
endmodule

module g_segment(input wire a, b, c, d, output wire out); //g_segment = a + bc' + b'c + cd'
    wire t0, t1, t2, t3;
    and2 a0(!b, c, t0);
    and2 a1(c, !d, t1);
    and2 a2(b, !c, t2);
    or3 o0(t0, t1, t2, t3);
    or2 o1(a, t3, out);
endmodule

module seven_segment(input wire [0:3] i);
    wire a_out, b_out, c_out, d_out, e_out, f_out, g_out;
    a_segment a_seg(i[0], i[1], i[2], i[3], a_out);
    b_segment b_seg(i[0], i[1], i[2], i[3], b_out);
    c_segment c_seg(i[0], i[1], i[2], i[3], c_out);
    d_segment d_seg(i[0], i[1], i[2], i[3], d_out);
    e_segment e_seg(i[0], i[1], i[2], i[3], e_out);
    f_segment f_seg(i[0], i[1], i[2], i[3], f_out);
    g_segment g_seg(i[0], i[1], i[2], i[3], g_out);
endmodule

SevenSegmentDisplay/seven_segment_tb.v
module seven_segment_tb;
    reg [0:3] ii;
    seven_segment seven_segment_display(.i(ii));
    initial
        begin
            ii = 4'b0000;#5
            ii = 4'b0001;#5
            ii = 4'b0010;#5
            ii = 4'b0011;#5
            ii = 4'b0100;#5
            ii = 4'b0101;#5
            ii = 4'b0110;#5
            ii = 4'b0111;#5
            ii = 4'b1000;#5
            ii = 4'b1001;#5
            ii = 4'b0000;
        end
    initial
        begin
            $dumpfile ("seven_segment_test.vcd");
            $dumpvars (0, seven_segment_tb);
        end
endmodule

DDCOProject/seven_segment_test.vcd
$date
	Sun Nov 19 00:20:39 2023
$end
$version
	Icarus Verilog
$end
$timescale
	1s
$end
$scope module seven_segment_tb $end
$var reg 4 ! ii [0:3] $end
$scope module seven_segment_display $end
$var wire 4 " i [0:3] $end
$var wire 1 # g_out $end
$var wire 1 $ f_out $end
$var wire 1 % e_out $end
$var wire 1 & d_out $end
$var wire 1 ' c_out $end
$var wire 1 ( b_out $end
$var wire 1 ) a_out $end
$scope module a_seg $end
$var wire 1 * a $end
$var wire 1 + b $end
$var wire 1 , c $end
$var wire 1 - d $end
$var wire 1 . t2 $end
$var wire 1 / t1 $end
$var wire 1 0 t0 $end
$var wire 1 ) out $end
$scope module a0 $end
$var wire 1 + i0 $end
$var wire 1 - i1 $end
$var wire 1 / o $end
$upscope $end
$scope module a1 $end
$var wire 1 1 i0 $end
$var wire 1 2 i1 $end
$var wire 1 . o $end
$upscope $end
$scope module o0 $end
$var wire 1 * i0 $end
$var wire 1 , i1 $end
$var wire 1 0 o $end
$upscope $end
$scope module o1 $end
$var wire 1 0 i0 $end
$var wire 1 / i1 $end
$var wire 1 . i2 $end
$var wire 1 3 t $end
$var wire 1 ) o $end
$scope module or2_0 $end
$var wire 1 0 i0 $end
$var wire 1 / i1 $end
$var wire 1 3 o $end
$upscope $end
$scope module or2_1 $end
$var wire 1 . i0 $end
$var wire 1 3 i1 $end
$var wire 1 ) o $end
$upscope $end
$upscope $end
$upscope $end
$scope module b_seg $end
$var wire 1 4 a $end
$var wire 1 5 b $end
$var wire 1 6 c $end
$var wire 1 7 d $end
$var wire 1 8 t1 $end
$var wire 1 9 t0 $end
$var wire 1 ( out $end
$scope module a0 $end
$var wire 1 : i0 $end
$var wire 1 ; i1 $end
$var wire 1 9 o $end
$upscope $end
$scope module a1 $end
$var wire 1 6 i0 $end
$var wire 1 7 i1 $end
$var wire 1 8 o $end
$upscope $end
$scope module o1 $end
$var wire 1 < i0 $end
$var wire 1 9 i1 $end
$var wire 1 8 i2 $end
$var wire 1 = t $end
$var wire 1 ( o $end
$scope module or2_0 $end
$var wire 1 < i0 $end
$var wire 1 9 i1 $end
$var wire 1 = o $end
$upscope $end
$scope module or2_1 $end
$var wire 1 8 i0 $end
$var wire 1 = i1 $end
$var wire 1 ( o $end
$upscope $end
$upscope $end
$upscope $end
$scope module c_seg $end
$var wire 1 > a $end
$var wire 1 ? b $end
$var wire 1 @ c $end
$var wire 1 A d $end
$var wire 1 ' out $end
$scope module o0 $end
$var wire 1 ? i0 $end
$var wire 1 B i1 $end
$var wire 1 A i2 $end
$var wire 1 C t $end
$var wire 1 ' o $end
$scope module or2_0 $end
$var wire 1 ? i0 $end
$var wire 1 B i1 $end
$var wire 1 C o $end
$upscope $end
$scope module or2_1 $end
$var wire 1 A i0 $end
$var wire 1 C i1 $end
$var wire 1 ' o $end
$upscope $end
$upscope $end
$upscope $end
$scope module d_seg $end
$var wire 1 D a $end
$var wire 1 E b $end
$var wire 1 F c $end
$var wire 1 G d $end
$var wire 1 H t4 $end
$var wire 1 I t3 $end
$var wire 1 J t2 $end
$var wire 1 K t1 $end
$var wire 1 L t0 $end
$var wire 1 & out $end
$scope module a0 $end
$var wire 1 M i0 $end
$var wire 1 N i1 $end
$var wire 1 L o $end
$upscope $end
$scope module a1 $end
$var wire 1 F i0 $end
$var wire 1 O i1 $end
$var wire 1 K o $end
$upscope $end
$scope module a2 $end
$var wire 1 E i0 $end
$var wire 1 P i1 $end
$var wire 1 G i2 $end
$var wire 1 Q t $end
$var wire 1 J o $end
$scope module and2_0 $end
$var wire 1 E i0 $end
$var wire 1 P i1 $end
$var wire 1 Q o $end
$upscope $end
$scope module and2_1 $end
$var wire 1 G i0 $end
$var wire 1 Q i1 $end
$var wire 1 J o $end
$upscope $end
$upscope $end
$scope module a3 $end
$var wire 1 R i0 $end
$var wire 1 F i1 $end
$var wire 1 I o $end
$upscope $end
$scope module o0 $end
$var wire 1 L i0 $end
$var wire 1 K i1 $end
$var wire 1 J i2 $end
$var wire 1 S t $end
$var wire 1 H o $end
$scope module or2_0 $end
$var wire 1 L i0 $end
$var wire 1 K i1 $end
$var wire 1 S o $end
$upscope $end
$scope module or2_1 $end
$var wire 1 J i0 $end
$var wire 1 S i1 $end
$var wire 1 H o $end
$upscope $end
$upscope $end
$scope module o1 $end
$var wire 1 H i0 $end
$var wire 1 I i1 $end
$var wire 1 D i2 $end
$var wire 1 T t $end
$var wire 1 & o $end
$scope module or2_0 $end
$var wire 1 H i0 $end
$var wire 1 I i1 $end
$var wire 1 T o $end
$upscope $end
$scope module or2_1 $end
$var wire 1 D i0 $end
$var wire 1 T i1 $end
$var wire 1 & o $end
$upscope $end
$upscope $end
$upscope $end
$scope module e_seg $end
$var wire 1 U a $end
$var wire 1 V b $end
$var wire 1 W c $end
$var wire 1 X d $end
$var wire 1 Y t1 $end
$var wire 1 Z t0 $end
$var wire 1 % out $end
$scope module a0 $end
$var wire 1 [ i0 $end
$var wire 1 \ i1 $end
$var wire 1 Z o $end
$upscope $end
$scope module a1 $end
$var wire 1 W i0 $end
$var wire 1 ] i1 $end
$var wire 1 Y o $end
$upscope $end
$scope module o0 $end
$var wire 1 Z i0 $end
$var wire 1 Y i1 $end
$var wire 1 % o $end
$upscope $end
$upscope $end
$scope module f_seg $end
$var wire 1 ^ a $end
$var wire 1 _ b $end
$var wire 1 ` c $end
$var wire 1 a d $end
$var wire 1 b t3 $end
$var wire 1 c t2 $end
$var wire 1 d t1 $end
$var wire 1 e t0 $end
$var wire 1 $ out $end
$scope module a0 $end
$var wire 1 f i0 $end
$var wire 1 g i1 $end
$var wire 1 e o $end
$upscope $end
$scope module a1 $end
$var wire 1 _ i0 $end
$var wire 1 h i1 $end
$var wire 1 d o $end
$upscope $end
$scope module a2 $end
$var wire 1 _ i0 $end
$var wire 1 i i1 $end
$var wire 1 c o $end
$upscope $end
$scope module o0 $end
$var wire 1 e i0 $end
$var wire 1 d i1 $end
$var wire 1 c i2 $end
$var wire 1 j t $end
$var wire 1 b o $end
$scope module or2_0 $end
$var wire 1 e i0 $end
$var wire 1 d i1 $end
$var wire 1 j o $end
$upscope $end
$scope module or2_1 $end
$var wire 1 c i0 $end
$var wire 1 j i1 $end
$var wire 1 b o $end
$upscope $end
$upscope $end
$scope module o1 $end
$var wire 1 ^ i0 $end
$var wire 1 b i1 $end
$var wire 1 $ o $end
$upscope $end
$upscope $end
$scope module g_seg $end
$var wire 1 k a $end
$var wire 1 l b $end
$var wire 1 m c $end
$var wire 1 n d $end
$var wire 1 o t3 $end
$var wire 1 p t2 $end
$var wire 1 q t1 $end
$var wire 1 r t0 $end
$var wire 1 # out $end
$scope module a0 $end
$var wire 1 s i0 $end
$var wire 1 m i1 $end
$var wire 1 r o $end
$upscope $end
$scope module a1 $end
$var wire 1 m i0 $end
$var wire 1 t i1 $end
$var wire 1 q o $end
$upscope $end
$scope module a2 $end
$var wire 1 l i0 $end
$var wire 1 u i1 $end
$var wire 1 p o $end
$upscope $end
$scope module o0 $end
$var wire 1 r i0 $end
$var wire 1 q i1 $end
$var wire 1 p i2 $end
$var wire 1 v t $end
$var wire 1 o o $end
$scope module or2_0 $end
$var wire 1 r i0 $end
$var wire 1 q i1 $end
$var wire 1 v o $end
$upscope $end
$scope module or2_1 $end
$var wire 1 p i0 $end
$var wire 1 v i1 $end
$var wire 1 o o $end
$upscope $end
$upscope $end
$scope module o1 $end
$var wire 1 k i0 $end
$var wire 1 o i1 $end
$var wire 1 # o $end
$upscope $end
$upscope $end
$upscope $end
$upscope $end
$enddefinitions $end
$comment Show the parameter values. $end
$dumpall
$end
#0
$dumpvars
0v
1u
1t
1s
0r
0q
0p
0o
0n
0m
0l
0k
1j
1i
1h
1g
1f
1e
0d
0c
1b
0a
0`
0_
0^
1]
1\
1[
1Z
0Y
0X
0W
0V
0U
1T
1S
1R
0Q
1P
1O
1N
1M
1L
0K
0J
0I
1H
0G
0F
0E
0D
1C
1B
0A
0@
0?
0>
1=
1<
1;
1:
19
08
07
06
05
04
03
12
11
00
0/
1.
0-
0,
0+
0*
1)
1(
1'
1&
1%
1$
0#
b0 "
b0 !
$end
#5
0&
0T
0$
0H
0b
0)
0S
0%
0j
0.
09
0L
0Z
0e
02
1-
0;
17
1A
0N
0O
1G
0\
0]
1X
0g
0i
1a
0t
1n
b1 !
b1 "
#10
1#
1&
1H
1o
13
1)
0'
1T
1S
1%
1v
10
1.
0C
1I
1L
1K
1Z
1Y
1r
1q
1,
12
0-
0:
16
1;
07
0B
1@
0A
0P
1F
1N
1O
0G
1W
1\
1]
0X
0f
0h
1`
1g
1i
0a
0u
1m
1t
0n
b10 !
b10 "
#15
0H
0S
0%
0.
18
1'
0L
0K
0Z
0Y
0q
02
1-
0;
17
1A
0N
0O
1G
0\
0]
1X
0g
0i
1a
0t
1n
b11 !
b11 "
#20
0)
0&
1$
03
0T
1j
1b
0v
00
19
08
1C
1'
1Q
0I
1d
1e
1c
1p
0r
01
1+
0,
12
0-
0<
15
1:
06
1;
07
1?
1B
0@
0A
0M
0R
1E
1P
0F
1N
1O
0G
0[
1V
0W
1\
1]
0X
1_
1f
1h
0`
1g
1i
0a
0s
1l
1u
0m
1t
0n
b100 !
b100 "
#25
1&
1)
0(
1T
13
0=
1H
1/
09
1J
0e
0c
02
1-
0;
17
1A
0N
0O
1G
0\
0]
1X
0g
0i
1a
0t
1n
b101 !
b101 "
#30
1&
1T
1S
1H
1%
0j
1v
10
0/
0Q
1K
0J
1Y
0d
1c
0p
1q
1,
12
0-
0:
16
1;
07
0B
1@
0A
0P
1F
1N
1O
0G
1W
1\
1]
0X
0f
0h
1`
1g
1i
0a
0u
1m
1t
0n
b110 !
b110 "
#35
0&
0T
0#
0H
0$
0o
1(
0S
0%
0b
0v
1/
18
0K
0Y
0c
0q
02
1-
0;
17
1A
0N
0O
1G
0\
0]
1X
0g
0i
1a
0t
1n
b111 !
b111 "
#40
1T
1H
1b
1S
1%
1j
1.
0/
1=
19
08
1&
1L
1Z
1$
1e
1#
1*
11
0+
0,
12
0-
14
1<
05
1:
06
1;
07
1>
0?
1B
0@
0A
1D
1M
1R
0E
1P
0F
1N
1O
0G
1U
1[
0V
0W
1\
1]
0X
1^
0_
1f
1h
0`
1g
1i
0a
1k
1s
0l
1u
0m
1t
0n
b1000 !
b1000 "
#45
0T
0H
0b
0S
0%
0j
0.
09
0L
0Z
0e
02
1-
0;
17
1A
0N
0O
1G
0\
0]
1X
0g
0i
1a
0t
1n
b1001 !
b1001 "
#50
1T
1H
1b
03
1S
1%
1j
00
1.
19
1&
1L
1Z
1$
1e
0#
0*
12
0-
04
1;
07
0>
0A
0D
1N
1O
0G
0U
1\
1]
0X
0^
1g
1i
0a
0k
1t
0n
b0 !
b0 "
