V_Labs/Lab4/MUX2to1.v
module mux2(input wire i0, i1, j, output wire o);
assign o = (j == 0) ? i0 : i1;
endmodule

V_Labs/Lab4/MUX2to1_tb.v
module TB;
reg A, B, S;
wire X;
mux2 newMUX(.i0(A), .i1(B), .j(S), .o(X));
initial
    begin
        B = 1'b0; A = 1'b0; S = 1'b0; #5
        B = 1'b0; A = 1'b0; S = 1'b1; #5
        B = 1'b0; A = 1'b1; S = 1'b0; #5
        B = 1'b0; A = 1'b1; S = 1'b1; #5
        B = 1'b1; A = 1'b0; S = 1'b0; #5
        B = 1'b1; A = 1'b0; S = 1'b1; #5
        B = 1'b1; A = 1'b1; S = 1'b0; #5
        B = 1'b1; A = 1'b1; S = 1'b1;
    end
initial
    begin
        $monitor($time, "B = %b, A = %b, S = %b, X = %b", B, A, S, X);
    end
initial 
    begin
        $dumpfile("MUX2to1_test.vcd");
        $dumpvars(0, TB);
    end
endmodule

V_Labs/Lab4/MUX2to1_test.vcd
$date
	Mon Aug 28 11:29:43 2023
$end
$version
	Icarus Verilog
$end
$timescale
	1s
$end
$scope module TB $end
$var wire 1 ! X $end
$var reg 1 " A $end
$var reg 1 # B $end
$var reg 1 $ S $end
$scope module newMUX $end
$var wire 1 " i0 $end
$var wire 1 # i1 $end
$var wire 1 $ j $end
$var wire 1 ! o $end
$upscope $end
$upscope $end
$enddefinitions $end
$comment Show the parameter values. $end
$dumpall
$end
#0
$dumpvars
0$
0#
0"
0!
$end
#5
1$
#10
1!
0$
1"
#15
0!
1$
#20
0$
0"
1#
#25
1!
1$
#30
0$
1"
#35
1$
