V_Labs/Lab2/circuit1.v
module circuit1(A, B, C, Y);
input A, B, C;
output Y;
wire w1;
assign w1 = B & C;
assign Y = A | w1;
endmodule

V_Labs/Lab2/circuit1_tb.v
module circuit1_tb;
reg A, B, C;
wire Y;
circuit1 M1(A, B, C, Y);
initial
    begin
        A=1'b0 ; B=1'b0 ; C=1'b0; #20
        A=1'b0 ; B=1'b0 ; C=1'b1; #20
        A=1'b0 ; B=1'b1 ; C=1'b0; #20
        A=1'b0 ; B=1'b1 ; C=1'b1; #20
        A=1'b1 ; B=1'b0 ; C=1'b0; #20
        A=1'b1 ; B=1'b0 ; C=1'b1; #20
        A=1'b1 ; B=1'b1 ; C=1'b0; #20
        A=1'b1 ; B=1'b1 ; C=1'b1;
    end
initial
    begin
        $monitor($time, "A = %b B = %b C = %b Y = %b", A, B, C, Y);
    end
initial
    begin
        $dumpfile ("circuit1_test.vcd");
        $dumpvars (0, circuit1_tb);
    end
endmodule

V_Labs/Lab2/circuit1_test.vcd
$date
	Tue Aug 22 09:00:43 2023
$end
$version
	Icarus Verilog
$end
$timescale
	1s
$end
$scope module circuit1_tb $end
$var wire 1 ! Y $end
$var reg 1 " A $end
$var reg 1 # B $end
$var reg 1 $ C $end
$scope module M1 $end
$var wire 1 " A $end
$var wire 1 # B $end
$var wire 1 $ C $end
$var wire 1 ! Y $end
$var wire 1 % w1 $end
$upscope $end
$upscope $end
$enddefinitions $end
$comment Show the parameter values. $end
$dumpall
$end
#0
$dumpvars
0%
0$
0#
0"
0!
$end
#20
1$
#40
0$
1#
#60
1!
1%
1$
#80
0%
0$
0#
1"
#100
1$
#120
0$
1#
#140
1%
1$
