V_Labs/Lab2/circuit2.v
module circuit2(A2, B2, C2, Y);
input A2, B2, C2;
output Y;
wire w1, w2, w3;
assign w1 = C2 & B2;
assign w2 = A2 | w1;
assign w3 = B2 & A2; 
assign Y = w2 | w3;
endmodule

V_Labs/Lab2/circuit2_tb.v
module circuit2_tb;
reg A, B, C;
wire Y;
circuit2 M1(A, B, C, Y);
initial
    begin
        A=1'b0 ; B=1'b0 ; C=1'b0; #20
        A=1'b0 ; B=1'b0 ; C=1'b1; #20
        A=1'b0 ; B=1'b1 ; C=1'b0; #20
        A=1'b0 ; B=1'b1 ; C=1'b1; #20
        A=1'b1 ; B=1'b0 ; C=1'b0; #20
        A=1'b1 ; B=1'b0 ; C=1'b1; #20
        A=1'b1 ; B=1'b1 ; C=1'b0; #20
        A=1'b1 ; B=1'b1 ; C=1'b1;
    end
initial
    begin
    $monitor($time, "A2 = %b B2 = %b C2 = %b Y = %b", A, B, C, Y);
    end
initial
    begin
        $dumpfile ("circuit2_test.vcd");
        $dumpvars (0, circuit2_tb);
    end
endmodule

V_Labs/Lab2/circuit2_test.vcd
$date
	Tue Aug 22 09:08:33 2023
$end
$version
	Icarus Verilog
$end
$timescale
	1s
$end
$scope module circuit2_tb $end
$var wire 1 ! Y $end
$var reg 1 " A $end
$var reg 1 # B $end
$var reg 1 $ C $end
$scope module M1 $end
$var wire 1 " A2 $end
$var wire 1 # B2 $end
$var wire 1 $ C2 $end
$var wire 1 ! Y $end
$var wire 1 % w1 $end
$var wire 1 & w2 $end
$var wire 1 ' w3 $end
$upscope $end
$upscope $end
$enddefinitions $end
$comment Show the parameter values. $end
$dumpall
$end
#0
$dumpvars
0'
0&
0%
0$
0#
0"
0!
$end
#20
1$
#40
0$
1#
#60
1!
1&
1%
1$
#80
0%
0$
0#
1"
#100
1$
#120
1'
0$
1#
#140
1%
1$
